HISTORY.rst
LICENSE
MANIFEST.in
README.rst
requirements.txt
run.py
setup.cfg
setup.py
clancy/__init__.py
clancy/__main__.py
clancy/clancy.py
clancy/config.py
clancy/engage.py
clancy/redoctober.py
clancy/utils.py
clancy.egg-info/PKG-INFO
clancy.egg-info/SOURCES.txt
clancy.egg-info/dependency_links.txt
clancy.egg-info/entry_points.txt
clancy.egg-info/not-zip-safe
clancy.egg-info/requires.txt
clancy.egg-info/top_level.txt