Metadata-Version: 1.1
Name: clancy
Version: 0.0.2
Summary: A command line client for Red October.
Home-page: https://github.com/pwyliu/clancy
Author: Paul Liu
Author-email: paul@ferociouspings.com
License: MIT
Keywords: Red October encryption security two man rule
Platform: UNKNOWN
Classifier: Development Status :: 3 - Alpha
Classifier: Intended Audience :: System Administrators
Classifier: Topic :: System :: Systems Administration
Classifier: License :: OSI Approved :: MIT License
Classifier: Programming Language :: Python :: 2.7
Classifier: Programming Language :: Python :: 2 :: Only
Classifier: Operating System :: POSIX :: Linux
